pycreg/__init__.py
pycreg/base.py
pycreg/constant.py
pycreg/cr_model/__init__.py
pycreg/cr_model/_base.py
pycreg/cr_model/_penalized.py
pycreg/utils/__init__.py
pycreg/utils/check.py
pycreg/utils/extmath.py
pycreg/utils/tools.py
pycvr-0.0.2.dist-info/LICENSE
pycvr-0.0.2.dist-info/METADATA
pycvr-0.0.2.dist-info/WHEEL
pycvr-0.0.2.dist-info/top_level.txt
pycvr-0.0.2.dist-info/RECORD
