Metadata-Version: 2.1
Name: pycvr
Version: 0.0.2
Summary: A Python Package for Convex Regression
Home-page: https://github.com/ConvexRegression/ConvexRegression
Author: Zhiqiang Liao
Author-email: zhiqiang.liao@aalto.fi
License: MIT
Download-URL: https://pypi.org/project/pysfa/
Keywords: ML,Prediction,Regression
Platform: UNKNOWN
Classifier: Development Status :: 5 - Production/Stable
Classifier: Intended Audience :: Science/Research
Classifier: Programming Language :: Python :: 3
Classifier: License :: OSI Approved :: MIT License
Classifier: Operating System :: OS Independent
License-File: LICENSE
Requires-Dist: numpy (>=1.19.2)
Requires-Dist: pandas (>=1.1.3)
